osc_ld_plugin/__init__.py
osc_ld_plugin/install_plugin.py
osc_ld_plugin/plugin.py
osc_ld_plugin-1.0.0.dist-info/METADATA
osc_ld_plugin-1.0.0.dist-info/WHEEL
osc_ld_plugin-1.0.0.dist-info/entry_points.txt
osc_ld_plugin-1.0.0.dist-info/RECORD
