Metadata-Version: 2.3
Name: osc_ld_plugin
Version: 1.0.0
Summary: An osc plugin to analyze failed build logs using logdetective
License: MIT
Keywords: osc,build,logdetective,obs,plugin
Author: Aazam Thakur
Author-email: aazamthakur@gmail.com
Requires-Python: >=3.11,<4.0
Classifier: Programming Language :: Python :: 3
Classifier: License :: OSI Approved :: MIT License
Classifier: Operating System :: OS Independent
Provides-Extra: logdetective
Requires-Dist: logdetective (>=1.7.0,<2.0.0) ; extra == "logdetective"
Requires-Dist: osc (>=1.17.0,<2.0.0)
Requires-Dist: requests
Project-URL: Homepage, https://github.com/openSUSE/logdetective-obs
Project-URL: Repository, https://github.com/openSUSE/logdetective-obs
